agentlogger/__init__.py
agentlogger/main.py
agentlogger/tests.py
agentlogger-0.1.2.dist-info/LICENSE
agentlogger-0.1.2.dist-info/METADATA
agentlogger-0.1.2.dist-info/WHEEL
agentlogger-0.1.2.dist-info/top_level.txt
agentlogger-0.1.2.dist-info/RECORD
