Metadata-Version: 2.1
Name: agentlogger
Version: 0.1.2
Summary: Simple, colorful debug logs and logfiles.
Home-page: https://github.com/AutonomousResearchGroup/agentlogger
Author: Moon
Author-email: shawmakesmagic@gmail.com
License: MIT
Classifier: Development Status :: 2 - Pre-Alpha
Classifier: Intended Audience :: Science/Research
Classifier: License :: OSI Approved :: MIT License
Classifier: Operating System :: POSIX :: Linux
Classifier: Programming Language :: Python :: 3
Classifier: Operating System :: MacOS :: MacOS X
Classifier: Operating System :: Microsoft :: Windows
License-File: LICENSE
